{ "type": "Feature",
    "geometry": {
        "type": "Point",
        "coordinates": [
            2.148685,
            41.393455
         ]
    },
    "properties": {
        "name": "elfari home",
        "popupContent": "Here I sit, playing music and tweeting the day away!",
        "title": "elfari",
        "marker-size": "medium",
        "marker-color": "#EE7600",
        "marker-symbol": "marker"
    }
}
